{"nm":"Main Scene","ddd":0,"h":1000,"w":1000,"meta":{"g":"@lottiefiles/creator 1.28.0"},"layers":[{"ty":0,"nm":"ulice_animace","sr":1,"st":-45.6,"op":254.4,"ip":0,"hd":false,"ddd":0,"bm":0,"hasMask":false,"ao":0,"ks":{"a":{"a":0,"k":[539,778]},"s":{"a":0,"k":[80,80]},"sk":{"a":0,"k":0},"p":{"a":0,"k":[-62.6822,622.1285]},"r":{"a":0,"k":0},"sa":{"a":0,"k":0},"o":{"a":0,"k":100}},"w":1986,"h":1086,"refId":"comp_0_e8d9b0a3-ea8a-413d-bff2-24288c4af137_59cf9900-2524-4b0c-8ed0-8f9bbcb23b72","ind":1}],"v":"5.7.0","fr":30,"op":240,"ip":0,"assets":[{"nm":"ulice_animace","id":"comp_0_e8d9b0a3-ea8a-413d-bff2-24288c4af137_59cf9900-2524-4b0c-8ed0-8f9bbcb23b72","fr":25,"layers":[{"ty":4,"nm":"vez Outlines","sr":1,"st":0,"op":313.2,"ip":0,"hd":false,"ddd":0,"bm":0,"hasMask":false,"ao":0,"ks":{"a":{"a":1,"k":[{"o":{"x":0.167,"y":0.167},"i":{"x":0.833,"y":0.833},"s":[133.292,735.06,0],"t":45.6},{"s":[133.292,735.06,0],"t":64.8}],"ix":1},"s":{"a":1,"k":[{"o":{"x":0.167,"y":0.167},"i":{"x":0.833,"y":0.833},"s":[115,115,100],"t":94.8},{"s":[120,120,100],"t":178.8}],"ix":6},"sk":{"a":0,"k":0},"p":{"a":1,"k":[{"o":{"x":0.333,"y":0},"i":{"x":0.667,"y":1},"s":[1236.133,1828.553,0],"t":45.6},{"s":[1596.133,1104.553,0],"t":64.8}],"ix":2},"r":{"a":1,"k":[{"o":{"x":0.333,"y":0},"i":{"x":0.667,"y":1},"s":[-21],"t":45.6},{"o":{"x":0.333,"y":0},"i":{"x":0.667,"y":1},"s":[15],"t":62.4},{"s":[8],"t":75.6}],"ix":10},"sa":{"a":0,"k":0},"o":{"a":0,"k":100,"ix":11}},"shapes":[{"ty":"gr","bm":0,"hd":false,"mn":"ADBE Vector Group","nm":"Group 1","ix":1,"cix":2,"np":2,"it":[{"ty":"sh","bm":0,"hd":false,"mn":"ADBE Vector Shape - Group","nm":"Path 1","ix":1,"d":1,"ks":{"a":0,"k":{"c":true,"i":[[-2.981,-5.656],[4.1,-2.161],[2.981,5.656],[-4.101,2.161]],"o":[[2.981,5.656],[-4.1,2.161],[-2.98,-5.656],[4.1,-2.162]],"v":[[7.424,-3.913],[5.397,10.24],[-7.425,3.914],[-5.397,-10.24]]},"ix":2}},{"ty":"fl","bm":0,"hd":false,"mn":"ADBE Vector Graphic - Fill","nm":"Fill 1","c":{"a":0,"k":[0.9686,0.8902,0.2784],"ix":4},"r":1,"o":{"a":0,"k":100,"ix":5}},{"ty":"tr","a":{"a":0,"k":[0,0],"ix":1},"s":{"a":0,"k":[100,100],"ix":3},"sk":{"a":0,"k":0,"ix":4},"p":{"a":0,"k":[10.655,12.652],"ix":2},"r":{"a":0,"k":0,"ix":6},"sa":{"a":0,"k":0,"ix":5},"o":{"a":0,"k":100,"ix":7}}]},{"ty":"gr","bm":0,"hd":false,"mn":"ADBE Vector Group","nm":"Group 2","ix":2,"cix":2,"np":2,"it":[{"ty":"sh","bm":0,"hd":false,"mn":"ADBE Vector Shape - Group","nm":"Path 1","ix":1,"d":1,"ks":{"a":0,"k":{"c":true,"i":[[0,-3.516],[3.197,0],[0,3.516],[-3.196,0]],"o":[[0,3.516],[-3.196,0],[0,-3.516],[3.197,0]],"v":[[5.788,0],[0,6.367],[-5.788,0],[0,-6.367]]},"ix":2}},{"ty":"fl","bm":0,"hd":false,"mn":"ADBE Vector Graphic - Fill","nm":"Fill 1","c":{"a":0,"k":[0.9686,0.8902,0.2784],"ix":4},"r":1,"o":{"a":0,"k":100,"ix":5}},{"ty":"tr","a":{"a":0,"k":[0,0],"ix":1},"s":{"a":0,"k":[100,100],"ix":3},"sk":{"a":0,"k":0,"ix":4},"p":{"a":0,"k":[25.414,105.836],"ix":2},"r":{"a":0,"k":0,"ix":6},"sa":{"a":0,"k":0,"ix":5},"o":{"a":0,"k":100,"ix":7}}]},{"ty":"gr","bm":0,"hd":false,"mn":"ADBE Vector Group","nm":"Group 3","ix":3,"cix":2,"np":2,"it":[{"ty":"sh","bm":0,"hd":false,"mn":"ADBE Vector Shape - Group","nm":"Path 1","ix":1,"d":1,"ks":{"a":0,"k":{"c":true,"i":[[0,-3.516],[3.197,0],[0,3.516],[-3.196,0]],"o":[[0,3.516],[-3.196,0],[0,-3.516],[3.197,0]],"v":[[5.788,0],[0,6.367],[-5.788,0],[0,-6.367]]},"ix":2}},{"ty":"fl","bm":0,"hd":false,"mn":"ADBE Vector Graphic - Fill","nm":"Fill 1","c":{"a":0,"k":[0.9686,0.8902,0.2784],"ix":4},"r":1,"o":{"a":0,"k":100,"ix":5}},{"ty":"tr","a":{"a":0,"k":[0,0],"ix":1},"s":{"a":0,"k":[100,100],"ix":3},"sk":{"a":0,"k":0,"ix":4},"p":{"a":0,"k":[99.498,90.788],"ix":2},"r":{"a":0,"k":0,"ix":6},"sa":{"a":0,"k":0,"ix":5},"o":{"a":0,"k":100,"ix":7}}]},{"ty":"gr","bm":0,"hd":false,"mn":"ADBE Vector Group","nm":"Group 4","ix":4,"cix":2,"np":2,"it":[{"ty":"sh","bm":0,"hd":false,"mn":"ADBE Vector Shape - Group","nm":"Path 1","ix":1,"d":1,"ks":{"a":0,"k":{"c":true,"i":[[-3.824,-16.34],[8.871,-2.075],[3.824,16.34],[-8.87,2.075]],"o":[[3.824,16.34],[-8.87,2.076],[-3.824,-16.34],[8.871,-2.076]],"v":[[16.062,-3.759],[6.923,29.586],[-16.062,3.759],[-6.924,-29.586]]},"ix":2}},{"ty":"fl","bm":0,"hd":false,"mn":"ADBE Vector Graphic - Fill","nm":"Fill 1","c":{"a":0,"k":[0.4706,0.6078,0.2431],"ix":4},"r":1,"o":{"a":0,"k":100,"ix":5}},{"ty":"tr","a":{"a":0,"k":[0,0],"ix":1},"s":{"a":0,"k":[100,100],"ix":3},"sk":{"a":0,"k":0,"ix":4},"p":{"a":0,"k":[139.723,341.69],"ix":2},"r":{"a":0,"k":0,"ix":6},"sa":{"a":0,"k":0,"ix":5},"o":{"a":0,"k":100,"ix":7}}]},{"ty":"gr","bm":0,"hd":false,"mn":"ADBE Vector Group","nm":"Group 5","ix":5,"cix":2,"np":2,"it":[{"ty":"sh","bm":0,"hd":false,"mn":"ADBE Vector Shape - Group","nm":"Path 1","ix":1,"d":1,"ks":{"a":0,"k":{"c":true,"i":[[0,0],[0,0],[0.226,14.256],[0,0],[0,0],[0,0],[0,0],[0,0],[4.034,15.545],[0,0],[-6.294,-2.934],[11.517,30.192],[-2.084,-5.335],[-15.235,-28.368],[-4.992,1.703],[0.145,7.814],[0,0],[0,0],[0,0],[0,0],[0,0],[0,0],[-5.654,-6.096]],"o":[[0,0],[0,0],[-0.225,-14.257],[0,0],[0,0],[0,0],[0,0],[0,0],[-3.917,-15.094],[0,0],[7.634,3.558],[-13.963,-36.603],[0,0],[15.892,29.591],[4.771,-1.627],[-0.136,-7.36],[0,0],[0,0],[0,0],[0,0],[0,0],[0,0],[5.653,6.097]],"v":[[92.21,112.863],[-47.788,151.57],[-29.024,131.351],[-38.357,111.471],[-29.587,102.42],[-36.387,76.943],[-42.654,71.904],[-38.005,67.532],[-47.331,10.681],[-76.293,-54.592],[-34.513,-9.906],[-47.331,-61.508],[-90.126,-146.234],[-29.174,-64.966],[0.07,-17.794],[2.311,-38.375],[-0.414,-68.221],[41.294,42.788],[48.367,45.822],[44.609,53.536],[52.244,78.789],[63.633,82.908],[64.863,100.923]]},"ix":2}},{"ty":"fl","bm":0,"hd":false,"mn":"ADBE Vector Graphic - Fill","nm":"Fill 1","c":{"a":0,"k":[0.4706,0.6078,0.2431],"ix":4},"r":1,"o":{"a":0,"k":100,"ix":5}},{"ty":"tr","a":{"a":0,"k":[0,0],"ix":1},"s":{"a":0,"k":[100,100],"ix":3},"sk":{"a":0,"k":0,"ix":4},"p":{"a":0,"k":[100.659,160.996],"ix":2},"r":{"a":0,"k":0,"ix":6},"sa":{"a":0,"k":0,"ix":5},"o":{"a":0,"k":100,"ix":7}}]},{"ty":"gr","bm":0,"hd":false,"mn":"ADBE Vector Group","nm":"Group 6","ix":6,"cix":2,"np":4,"it":[{"ty":"sh","bm":0,"hd":false,"mn":"ADBE Vector Shape - Group","nm":"Path 1","ix":1,"d":1,"ks":{"a":0,"k":{"c":true,"i":[[-31.341,-439.576],[0,0],[17.94,110.535],[0,0],[0,0]],"o":[[0,0],[0,0],[-17.943,-110.547],[0,0],[0,0]],"v":[[79.047,264.69],[-22.905,260.938],[-43.741,-63.181],[-79.047,-218.873],[12.322,-243.326]]},"ix":2}},{"ty":"fl","bm":0,"hd":false,"mn":"ADBE Vector Graphic - Fill","nm":"Fill 1","c":{"a":0,"k":[0.3451,0.2078,0.0784],"ix":4},"r":1,"o":{"a":0,"k":100,"ix":5}},{"ty":"tr","a":{"a":0,"k":[0,0],"ix":1},"s":{"a":0,"k":[100,100],"ix":3},"sk":{"a":0,"k":0,"ix":4},"p":{"a":0,"k":[155.287,517.181],"ix":2},"r":{"a":0,"k":0,"ix":6},"sa":{"a":0,"k":0,"ix":5},"o":{"a":0,"k":100,"ix":7}}]}],"ind":1},{"ty":4,"nm":"masle Outlines","sr":1,"st":0,"op":309.6,"ip":75.6,"hd":false,"ddd":0,"bm":0,"hasMask":true,"ao":0,"ks":{"a":{"a":0,"k":[342.63,141.29,0],"ix":1},"s":{"a":1,"k":[{"o":{"x":0.167,"y":0.167},"i":{"x":0.833,"y":0.833},"s":[116,116,100],"t":94.8},{"s":[120,120,100],"t":178.8}],"ix":6},"sk":{"a":0,"k":0},"p":{"a":1,"k":[{"o":{"x":0.167,"y":0.167},"i":{"x":0.833,"y":0.833},"s":[1565.971,268.764,0],"t":64.8},{"o":{"x":0.333,"y":0},"i":{"x":0.667,"y":1},"s":[1565.971,268.764,0],"t":94.8},{"s":[1571.971,230.764,0],"t":178.8}],"ix":2},"r":{"a":0,"k":0,"ix":10},"sa":{"a":0,"k":0},"o":{"a":0,"k":100,"ix":11}},"ef":[{"ty":5,"mn":"ADBE CM WiggleGelatin","nm":"Wiggle - gelatin","ix":1,"en":1,"ef":[{"ty":0,"mn":"ADBE CM WiggleGelatin-0001","nm":"Wiggle Speed (wigs/sec)","ix":1,"v":{"a":0,"k":1,"ix":1}},{"ty":0,"mn":"ADBE CM WiggleGelatin-0002","nm":"Wiggle Amount","ix":2,"v":{"a":0,"k":20,"ix":2}}]},{"ty":5,"mn":"ADBE Geometry2","nm":"(Transform)","ix":2,"en":1,"ef":[{"ty":3,"mn":"ADBE Geometry2-0001","nm":"Anchor Point","ix":1,"v":{"a":0,"k":[0,0],"ix":1}},{"ty":3,"mn":"ADBE Geometry2-0002","nm":"Position","ix":2,"v":{"a":0,"k":[0,0],"ix":2}},{"ty":7,"mn":"ADBE Geometry2-0011","nm":"Uniform Scale","ix":3,"v":{"a":0,"k":0,"ix":3}},{"ty":0,"mn":"ADBE Geometry2-0003","nm":"Scale Height","ix":4,"v":{"a":0,"k":100,"ix":4}},{"ty":0,"mn":"ADBE Geometry2-0004","nm":"Scale Width","ix":5,"v":{"a":0,"k":100,"ix":5}},{"ty":0,"mn":"ADBE Geometry2-0005","nm":"Skew","ix":6,"v":{"a":0,"k":0,"ix":6}},{"ty":0,"mn":"ADBE Geometry2-0006","nm":"Skew Axis","ix":7,"v":{"a":0,"k":0,"ix":7}},{"ty":0,"mn":"ADBE Geometry2-0007","nm":"Rotation","ix":8,"v":{"a":0,"k":0,"ix":8}},{"ty":0,"mn":"ADBE Geometry2-0008","nm":"Opacity","ix":9,"v":{"a":0,"k":100,"ix":9}},{"ty":7,"mn":"ADBE Geometry2-0009","nm":"Use Composition’s Shutter Angle","ix":10,"v":{"a":0,"k":1,"ix":10}},{"ty":0,"mn":"ADBE Geometry2-0010","nm":"Shutter Angle","ix":11,"v":{"a":0,"k":0,"ix":11}},{"ty":7,"mn":"ADBE Geometry2-0012","nm":"Sampling","ix":12,"v":{"a":0,"k":1,"ix":12}}]}],"masksProperties":[{"nm":"Mask 2","inv":false,"mode":"a","x":{"a":0,"k":0,"ix":4},"o":{"a":0,"k":100,"ix":3},"pt":{"a":1,"k":[{"o":{"x":0.167,"y":0.167},"i":{"x":0.833,"y":0.833},"s":[{"c":true,"i":[[105.174,0],[0,-133.029],[-105.174,0],[0,133.029]],"o":[[-105.174,0],[0,133.029],[105.174,0],[0,-133.029]],"v":[[542.857,-79.917],[352.422,160.952],[542.857,401.822],[733.292,160.952]]}],"t":75.6},{"s":[{"c":true,"i":[[105.174,0],[0,-133.029],[-105.174,0],[0,133.028]],"o":[[-105.174,0],[0,133.028],[105.174,0],[0,-133.029]],"v":[[168.899,-93.636],[-21.536,147.234],[168.899,388.104],[359.333,147.234]]}],"t":90}],"ix":1}}],"shapes":[{"ty":"gr","bm":0,"hd":false,"mn":"ADBE Vector Group","nm":"Group 1","ix":1,"cix":2,"np":2,"it":[{"ty":"sh","bm":0,"hd":false,"mn":"ADBE Vector Shape - Group","nm":"Path 1","ix":1,"d":1,"ks":{"a":0,"k":{"c":true,"i":[[0,0],[-62.111,13.336],[0,0],[55.234,-8.413],[0,0],[0,0]],"o":[[0,0],[28.642,-6.15],[0,0],[-40.51,6.17],[0,0],[0,0]],"v":[[-126.255,45.327],[-10.938,-16.174],[176.38,-32.157],[-30.8,-36.914],[-176.38,20.113],[-127.507,17.29]]},"ix":2}},{"ty":"fl","bm":0,"hd":false,"mn":"ADBE Vector Graphic - Fill","nm":"Fill 1","c":{"a":0,"k":[0.2314,0.5412,0.7882],"ix":4},"r":1,"o":{"a":0,"k":100,"ix":5}},{"ty":"tr","a":{"a":0,"k":[0,0],"ix":1},"s":{"a":0,"k":[100,100],"ix":3},"sk":{"a":0,"k":0,"ix":4},"p":{"a":0,"k":[176.63,172.876],"ix":2},"r":{"a":0,"k":0,"ix":6},"sa":{"a":0,"k":0,"ix":5},"o":{"a":0,"k":100,"ix":7}}]},{"ty":"gr","bm":0,"hd":false,"mn":"ADBE Vector Group","nm":"Group 2","ix":2,"cix":2,"np":2,"it":[{"ty":"sh","bm":0,"hd":false,"mn":"ADBE Vector Shape - Group","nm":"Path 1","ix":1,"d":1,"ks":{"a":0,"k":{"c":true,"i":[[0,0],[-58.077,-26.161],[0,0],[52.343,19.893],[0,0],[0,0]],"o":[[0,0],[26.781,12.065],[0,0],[-38.389,-14.59],[0,0],[0,0]],"v":[[-113.157,-69.855],[-12.753,14.667],[167.296,69.855],[-36.378,30.767],[-167.296,-55.768],[-120.047,-42.687]]},"ix":2}},{"ty":"fl","bm":0,"hd":false,"mn":"ADBE Vector Graphic - Fill","nm":"Fill 1","c":{"a":0,"k":[0.9137,0.2784,0.3373],"ix":4},"r":1,"o":{"a":0,"k":100,"ix":5}},{"ty":"tr","a":{"a":0,"k":[0,0],"ix":1},"s":{"a":0,"k":[100,100],"ix":3},"sk":{"a":0,"k":0,"ix":4},"p":{"a":0,"k":[185.542,70.105],"ix":2},"r":{"a":0,"k":0,"ix":6},"sa":{"a":0,"k":0,"ix":5},"o":{"a":0,"k":100,"ix":7}}]},{"ty":"gr","bm":0,"hd":false,"mn":"ADBE Vector Group","nm":"Group 3","ix":3,"cix":2,"np":2,"it":[{"ty":"sh","bm":0,"hd":false,"mn":"ADBE Vector Shape - Group","nm":"Path 1","ix":1,"d":1,"ks":{"a":0,"k":{"c":true,"i":[[0,0],[-58.085,65.551],[-43.442,38.95],[0,0],[22.581,-10.639],[22.659,-9.646],[25.592,-14.552],[0,0],[0,0]],"o":[[0,0],[58.085,-65.552],[9.244,-8.288],[0,0],[-22.58,10.64],[-33.678,14.336],[-38.808,22.064],[0,0],[0,0]],"v":[[-160.392,54.698],[-21.743,-10.775],[132.861,-56.029],[162.691,-76.043],[126.848,-33.628],[37.363,-17.912],[-53.239,54.263],[-162.691,76.209],[-146.462,64.784]]},"ix":2}},{"ty":"fl","bm":0,"hd":false,"mn":"ADBE Vector Graphic - Fill","nm":"Fill 1","c":{"a":0,"k":[0.9098,0.5608,0.7373],"ix":4},"r":1,"o":{"a":0,"k":100,"ix":5}},{"ty":"tr","a":{"a":0,"k":[0,0],"ix":1},"s":{"a":0,"k":[100,100],"ix":3},"sk":{"a":0,"k":0,"ix":4},"p":{"a":0,"k":[190.148,216.003],"ix":2},"r":{"a":0,"k":0,"ix":6},"sa":{"a":0,"k":0,"ix":5},"o":{"a":0,"k":100,"ix":7}}]}],"ind":2}]}]}